README.md
setup.cfg
setup.py
python_weed.egg-info/PKG-INFO
python_weed.egg-info/SOURCES.txt
python_weed.egg-info/dependency_links.txt
python_weed.egg-info/requires.txt
python_weed.egg-info/top_level.txt
test/test_weed.py
weed/__init__.py
weed/conf.py
weed/filer.py
weed/master.py
weed/operation.py
weed/test_conf.py
weed/test_volume.py
weed/util.py
weed/version.py
weed/volume.py