Metadata-Version: 2.1
Name: python-weed
Version: 0.6.0
Summary: A python module for seaweedfs(old name: weed-fs)
Home-page: https://github.com/darkdarkfruit/python-weed
Author: darkdarkfruit
Author-email: darkdarkfruit@gmail.com
License: MIT
Platform: any
Classifier: Development Status :: 4 - Beta
Classifier: Intended Audience :: Developers
Classifier: License :: OSI Approved :: MIT License
Classifier: Operating System :: OS Independent
Classifier: Programming Language :: Python
Classifier: Topic :: Internet
Classifier: Topic :: Software Development :: Libraries :: Python Modules
Requires: requests
